{"result": {"query": ":facetid:toc:\"db/conf/pakdd/pakdd2020-1.bht\"", "status": {"@code": "200", "text": "OK"}, "time": {"@unit": "msecs", "text": "134.22"}, "completions": {"@total": "1", "@computed": "1", "@sent": "1", "c": {"@sc": "68", "@dc": "68", "@oc": "68", "@id": "31667114", "text": ":facetid:toc:db/conf/pakdd/pakdd2020-1.bht"}}, "hits": {"@total": "68", "@computed": "68", "@sent": "68", "@first": "0", "hit": [{"@score": "1", "@id": "579742", "info": {"authors": {"author": [{"@pid": "27/4390-3", "text": "Yi Han 0003"}, {"@pid": "47/5584", "text": "Shanika Karunasekera"}, {"@pid": "73/1139", "text": "Christopher Leckie"}]}, "title": "Image Analysis Enhanced Event Detection from Geo-Tagged Tweet Streams.", "venue": "PAKDD", "pages": "398-410", "year": "2020", "type": "Conference and Workshop Papers", "access": "closed", "key": "conf/pakdd/0003KL20", "doi": "10.1007/978-3-030-47426-3_31", "ee": "https://doi.org/10.1007/978-3-030-47426-3_31", "url": "https://dblp.org/rec/conf/pakdd/0003KL20"}, "url": "URL#579742"}, {"@score": "1", "@id": "579743", "info": {"authors": {"author": [{"@pid": "01/1844-6", "text": "Zhenyu Zhang 0006"}, {"@pid": "95/10266-2", "text": "Bowen Yu 0002"}, {"@pid": "56/7911", "text": "Tingwen Liu"}, {"@pid": "40/3934", "text": "Dong Wang"}]}, "title": "Strong Baselines for Author Name Disambiguation with and Without Neural Networks.", "venue": "PAKDD", "pages": "369-381", "year": "2020", "type": "Conference and Workshop Papers", "access": "closed", "key": "conf/pakdd/0006YLW20", "doi": "10.1007/978-3-030-47426-3_29", "ee": "https://doi.org/10.1007/978-3-030-47426-3_29", "url": "https://dblp.org/rec/conf/pakdd/0006YLW20"}, "url": "URL#579743"}, {"@score": "1", "@id": "579745", "info": {"authors": {"author": [{"@pid": "119/1223-1", "text": "Lei Bai 0001"}, {"@pid": "56/6651", "text": "Lina Yao"}, {"@pid": "51/8330", "text": "Xianzhi Wang 0001"}, {"@pid": "42/840", "text": "Salil S. Kanhere"}, {"@pid": "181/1848", "text": "Yang Xiao"}]}, "title": "Prototype Similarity Learning for Activity Recognition.", "venue": "PAKDD", "pages": "649-661", "year": "2020", "type": "Conference and Workshop Papers", "access": "closed", "key": "conf/pakdd/BaiY0KX20", "doi": "10.1007/978-3-030-47426-3_50", "ee": "https://doi.org/10.1007/978-3-030-47426-3_50", "url": "https://dblp.org/rec/conf/pakdd/BaiY0KX20"}, "url": "URL#579745"}, {"@score": "1", "@id": "579746", "info": {"authors": {"author": [{"@pid": "157/6439", "text": "Oana Balalau"}, {"@pid": "240/9148", "text": "Sagar Goyal"}]}, "title": "SubRank - Subgraph Embeddings via a Subgraph Proximity Measure.", "venue": "PAKDD", "pages": "487-498", "year": "2020", "type": "Conference and Workshop Papers", "access": "closed", "key": "conf/pakdd/BalalauG20", "doi": "10.1007/978-3-030-47426-3_38", "ee": "https://doi.org/10.1007/978-3-030-47426-3_38", "url": "https://dblp.org/rec/conf/pakdd/BalalauG20"}, "url": "URL#579746"}, {"@score": "1", "@id": "579748", "info": {"authors": {"author": [{"@pid": "264/6389", "text": "Achraf Bennis"}, {"@pid": "34/2688", "text": "Sandrine Mouysset"}, {"@pid": "30/2092", "text": "Mathieu Serrurier"}]}, "title": "Estimation of Conditional Mixture Weibull Distribution with Right Censored Data Using Neural Network for Time-to-Event Analysis.", "venue": "PAKDD", "pages": "687-698", "year": "2020", "type": "Conference and Workshop Papers", "access": "closed", "key": "conf/pakdd/BennisMS20", "doi": "10.1007/978-3-030-47426-3_53", "ee": "https://doi.org/10.1007/978-3-030-47426-3_53", "url": "https://dblp.org/rec/conf/pakdd/BennisMS20"}, "url": "URL#579748"}, {"@score": "1", "@id": "579749", "info": {"authors": {"author": [{"@pid": "255/5945", "text": "Rajarshi Bhattacharjee"}, {"@pid": "17/2536", "text": "Naresh Manwani"}]}, "title": "Online Algorithms for Multiclass Classification Using Partial Labels.", "venue": "PAKDD", "pages": "249-260", "year": "2020", "type": "Conference and Workshop Papers", "access": "closed", "key": "conf/pakdd/BhattacharjeeM20", "doi": "10.1007/978-3-030-47426-3_20", "ee": "https://doi.org/10.1007/978-3-030-47426-3_20", "url": "https://dblp.org/rec/conf/pakdd/BhattacharjeeM20"}, "url": "URL#579749"}, {"@score": "1", "@id": "579750", "info": {"authors": {"author": [{"@pid": "156/9559", "text": "Felix Borutta"}, {"@pid": "141/5283", "text": "Daniyal Kazempour"}, {"@pid": "264/6396", "text": "Felix Mathy"}, {"@pid": "k/PeerKroger", "text": "Peer Kr\u00f6ger"}, {"@pid": "s/ThomasSeidl1", "text": "Thomas Seidl 0001"}]}, "title": "Detecting Arbitrarily Oriented Subspace Clusters in Data Streams Using Hough Transform.", "venue": "PAKDD", "pages": "356-368", "year": "2020", "type": "Conference and Workshop Papers", "access": "closed", "key": "conf/pakdd/BoruttaKMK020", "doi": "10.1007/978-3-030-47426-3_28", "ee": "https://doi.org/10.1007/978-3-030-47426-3_28", "url": "https://dblp.org/rec/conf/pakdd/BoruttaKMK020"}, "url": "URL#579750"}, {"@score": "1", "@id": "579751", "info": {"authors": {"author": [{"@pid": "251/8679", "text": "Xiaosha Cai"}, {"@pid": "94/3756-1", "text": "Dong Huang 0001"}, {"@pid": "69/9023", "text": "Chang-Dong Wang"}, {"@pid": "32/228", "text": "Chee-Keong Kwoh 0001"}]}, "title": "Spectral Clustering by Subspace Randomization and Graph Fusion for High-Dimensional Data.", "venue": "PAKDD", "pages": "330-342", "year": "2020", "type": "Conference and Workshop Papers", "access": "closed", "key": "conf/pakdd/CaiHWK20", "doi": "10.1007/978-3-030-47426-3_26", "ee": "https://doi.org/10.1007/978-3-030-47426-3_26", "url": "https://dblp.org/rec/conf/pakdd/CaiHWK20"}, "url": "URL#579751"}, {"@score": "1", "@id": "579752", "info": {"authors": {"author": [{"@pid": "264/6400", "text": "Hieu K. Cao"}, {"@pid": "243/4468", "text": "Han K. Cao"}, {"@pid": "06/2545", "text": "Binh T. Nguyen 0001"}]}, "title": "DELAFO - An Efficient Portfolio Optimization Using Deep Neural Networks.", "venue": "PAKDD", "pages": "623-635", "year": "2020", "type": "Conference and Workshop Papers", "access": "closed", "key": "conf/pakdd/CaoCN20", "doi": "10.1007/978-3-030-47426-3_48", "ee": "https://doi.org/10.1007/978-3-030-47426-3_48", "url": "https://dblp.org/rec/conf/pakdd/CaoCN20"}, "url": "URL#579752"}, {"@score": "1", "@id": "579754", "info": {"authors": {"author": [{"@pid": "220/4030", "text": "Jiayin Chen"}, {"@pid": "171/1101", "text": "Xiaolong Gong"}, {"@pid": "16/3283-55", "text": "Xi Chen 0055"}, {"@pid": "58/6005", "text": "Zhiyi Ma"}]}, "title": "Attribute-Driven Capsule Network for Entity Relation Prediction.", "venue": "PAKDD", "pages": "675-686", "year": "2020", "type": "Conference and Workshop Papers", "access": "closed", "key": "conf/pakdd/ChenGCM20", "doi": "10.1007/978-3-030-47426-3_52", "ee": "https://doi.org/10.1007/978-3-030-47426-3_52", "url": "https://dblp.org/rec/conf/pakdd/ChenGCM20"}, "url": "URL#579754"}, {"@score": "1", "@id": "579755", "info": {"authors": {"author": [{"@pid": "39/9713", "text": "Hsi-Wen Chen"}, {"@pid": "86/10294", "text": "Hong-Han Shuai"}, {"@pid": "76/6381", "text": "Sheng-De Wang"}, {"@pid": "85/318", "text": "De-Nian Yang"}]}, "title": "Quality-Aware Streaming Network Embedding with Memory Refreshing.", "venue": "PAKDD", "pages": "448-461", "year": "2020", "type": "Conference and Workshop Papers", "access": "closed", "key": "conf/pakdd/ChenSWY20", "doi": "10.1007/978-3-030-47426-3_35", "ee": "https://doi.org/10.1007/978-3-030-47426-3_35", "url": "https://dblp.org/rec/conf/pakdd/ChenSWY20"}, "url": "URL#579755"}, {"@score": "1", "@id": "579757", "info": {"authors": {"author": [{"@pid": "89/5615", "text": "Bo Chen"}, {"@pid": "05/3499-1", "text": "Jing Zhang 0001"}, {"@pid": "246/5460", "text": "Xiaobin Tang"}, {"@pid": "52/4150-1", "text": "Hong Chen 0001"}, {"@pid": "03/6827-1", "text": "Cuiping Li 0001"}]}, "title": "JarKA - Modeling Attribute Interactions for Cross-lingual Knowledge Alignment.", "venue": "PAKDD", "pages": "845-856", "year": "2020", "type": "Conference and Workshop Papers", "access": "closed", "key": "conf/pakdd/ChenZT0L20", "doi": "10.1007/978-3-030-47426-3_65", "ee": "https://doi.org/10.1007/978-3-030-47426-3_65", "url": "https://dblp.org/rec/conf/pakdd/ChenZT0L20"}, "url": "URL#579757"}, {"@score": "1", "@id": "579758", "info": {"authors": {"author": [{"@pid": "92/3741", "text": "Gianni Costa"}, {"@pid": "23/1461", "text": "Riccardo Ortale"}]}, "title": "Collaborative Recommendation of Temporally-Discounted Tag-Based Expertise for Community Question Answering.", "venue": "PAKDD", "pages": "41-52", "year": "2020", "type": "Conference and Workshop Papers", "access": "closed", "key": "conf/pakdd/CostaO20", "doi": "10.1007/978-3-030-47426-3_4", "ee": "https://doi.org/10.1007/978-3-030-47426-3_4", "url": "https://dblp.org/rec/conf/pakdd/CostaO20"}, "url": "URL#579758"}, {"@score": "1", "@id": "579759", "info": {"authors": {"author": [{"@pid": "197/3968", "text": "Tianyu Cui"}, {"@pid": "13/10808", "text": "Gaopeng Gou"}, {"@pid": "96/372", "text": "Gang Xiong"}]}, "title": "6GCVAE - Gated Convolutional Variational Autoencoder for IPv6 Target Generation.", "venue": "PAKDD", "pages": "609-622", "year": "2020", "type": "Conference and Workshop Papers", "access": "closed", "key": "conf/pakdd/CuiGX20", "doi": "10.1007/978-3-030-47426-3_47", "ee": "https://doi.org/10.1007/978-3-030-47426-3_47", "url": "https://dblp.org/rec/conf/pakdd/CuiGX20"}, "url": "URL#579759"}, {"@score": "1", "@id": "579760", "info": {"authors": {"author": [{"@pid": "228/9373", "text": "Sonam Damani"}, {"@pid": "198/5513", "text": "Kedhar Nath Narahari"}, {"@pid": "177/1941", "text": "Ankush Chatterjee"}, {"@pid": "g/ManishGupta1", "text": "Manish Gupta 0001"}, {"@pid": "182/1992", "text": "Puneet Agrawal"}]}, "title": "Optimized Transformer Models for FAQ Answering.", "venue": "PAKDD", "pages": "235-248", "year": "2020", "type": "Conference and Workshop Papers", "access": "closed", "key": "conf/pakdd/DamaniNCGA20", "doi": "10.1007/978-3-030-47426-3_19", "ee": "https://doi.org/10.1007/978-3-030-47426-3_19", "url": "https://dblp.org/rec/conf/pakdd/DamaniNCGA20"}, "url": "URL#579760"}, {"@score": "1", "@id": "579763", "info": {"authors": {"author": [{"@pid": "198/1195", "text": "Shuangfei Fan"}, {"@pid": "93/10793", "text": "Bert Huang"}]}, "title": "Attention-Based Graph Evolution.", "venue": "PAKDD", "pages": "436-447", "year": "2020", "type": "Conference and Workshop Papers", "access": "closed", "key": "conf/pakdd/FanH20", "doi": "10.1007/978-3-030-47426-3_34", "ee": "https://doi.org/10.1007/978-3-030-47426-3_34", "url": "https://dblp.org/rec/conf/pakdd/FanH20"}, "url": "URL#579763"}, {"@score": "1", "@id": "579765", "info": {"authors": {"author": [{"@pid": "97/10652", "text": "Ahmed Fathy"}, {"@pid": "21/2083", "text": "Kan Li"}]}, "title": "TemporalGAT - Attention-Based Dynamic Graph Representation Learning.", "venue": "PAKDD", "pages": "413-423", "year": "2020", "type": "Conference and Workshop Papers", "access": "closed", "key": "conf/pakdd/FathyL20", "doi": "10.1007/978-3-030-47426-3_32", "ee": "https://doi.org/10.1007/978-3-030-47426-3_32", "url": "https://dblp.org/rec/conf/pakdd/FathyL20"}, "url": "URL#579765"}, {"@score": "1", "@id": "579769", "info": {"authors": {"author": [{"@pid": "264/6383", "text": "Gao-Jie Han"}, {"@pid": "08/1043", "text": "Xiaofang Zhang"}, {"@pid": "181/2812", "text": "Hao Wang"}, {"@pid": "264/6382", "text": "Chen-Guang Mao"}]}, "title": "Curiosity-Driven Variational Autoencoder for Deep Q Network.", "venue": "PAKDD", "pages": "764-775", "year": "2020", "type": "Conference and Workshop Papers", "access": "closed", "key": "conf/pakdd/HanZWM20", "doi": "10.1007/978-3-030-47426-3_59", "ee": "https://doi.org/10.1007/978-3-030-47426-3_59", "url": "https://dblp.org/rec/conf/pakdd/HanZWM20"}, "url": "URL#579769"}, {"@score": "1", "@id": "579770", "info": {"authors": {"author": [{"@pid": "257/3084", "text": "Zohair Raza Hassan"}, {"@pid": "78/7323", "text": "Mudassir Shabbir"}, {"@pid": "77/9060", "text": "Imdadullah Khan"}, {"@pid": "79/11046", "text": "Waseem Abbas"}]}, "title": "Estimating Descriptors for Large Graphs.", "venue": "PAKDD", "pages": "779-791", "year": "2020", "type": "Conference and Workshop Papers", "access": "closed", "key": "conf/pakdd/HassanSKA20", "doi": "10.1007/978-3-030-47426-3_60", "ee": "https://doi.org/10.1007/978-3-030-47426-3_60", "url": "https://dblp.org/rec/conf/pakdd/HassanSKA20"}, "url": "URL#579770"}, {"@score": "1", "@id": "579776", "info": {"authors": {"author": [{"@pid": "91/6423", "text": "Dino Ienco"}, {"@pid": "135/5203", "text": "Roberto Interdonato"}]}, "title": "Deep Multivariate Time Series Embedding Clustering via Attentive-Gated Autoencoder.", "venue": "PAKDD", "pages": "318-329", "year": "2020", "type": "Conference and Workshop Papers", "access": "closed", "key": "conf/pakdd/IencoI20", "doi": "10.1007/978-3-030-47426-3_25", "ee": "https://doi.org/10.1007/978-3-030-47426-3_25", "url": "https://dblp.org/rec/conf/pakdd/IencoI20"}, "url": "URL#579776"}, {"@score": "1", "@id": "579780", "info": {"authors": {"author": [{"@pid": "236/4830", "text": "Shayan Jawed"}, {"@pid": "117/4936", "text": "Josif Grabocka"}, {"@pid": "s/LarsSchmidtThieme", "text": "Lars Schmidt-Thieme"}]}, "title": "Self-supervised Learning for Semi-supervised Time Series Classification.", "venue": "PAKDD", "pages": "499-511", "year": "2020", "type": "Conference and Workshop Papers", "access": "closed", "key": "conf/pakdd/JawedGS20", "doi": "10.1007/978-3-030-47426-3_39", "ee": "https://doi.org/10.1007/978-3-030-47426-3_39", "url": "https://dblp.org/rec/conf/pakdd/JawedGS20"}, "url": "URL#579780"}, {"@score": "1", "@id": "579781", "info": {"authors": {"author": [{"@pid": "20/11432", "text": "Yiwen Jiang"}, {"@pid": "58/1874", "text": "Wei Tang"}, {"@pid": "53/11537", "text": "Neng Gao"}, {"@pid": "12/6661", "text": "Ji Xiang"}, {"@pid": "144/6291", "text": "Chenyang Tu"}, {"@pid": "82/0", "text": "Min Li"}]}, "title": "Multiple Demographic Attributes Prediction in Mobile and Sensor Devices.", "venue": "PAKDD", "pages": "857-868", "year": "2020", "type": "Conference and Workshop Papers", "access": "closed", "key": "conf/pakdd/JiangTGXTL20", "doi": "10.1007/978-3-030-47426-3_66", "ee": "https://doi.org/10.1007/978-3-030-47426-3_66", "url": "https://dblp.org/rec/conf/pakdd/JiangTGXTL20"}, "url": "URL#579781"}, {"@score": "1", "@id": "579783", "info": {"authors": {"author": [{"@pid": "264/6401", "text": "Xianxian Jin"}, {"@pid": "143/6326", "text": "Xinzhi Wang"}, {"@pid": "63/4996", "text": "Xiangfeng Luo"}, {"@pid": "226/4553", "text": "Subin Huang"}, {"@pid": "176/3625", "text": "Shengwei Gu"}]}, "title": "Inter-sentence and Implicit Causality Extraction from Chinese Corpus.", "venue": "PAKDD", "pages": "739-751", "year": "2020", "type": "Conference and Workshop Papers", "access": "closed", "key": "conf/pakdd/JinWLHG20", "doi": "10.1007/978-3-030-47426-3_57", "ee": "https://doi.org/10.1007/978-3-030-47426-3_57", "url": "https://dblp.org/rec/conf/pakdd/JinWLHG20"}, "url": "URL#579783"}, {"@score": "1", "@id": "579786", "info": {"authors": {"author": [{"@pid": "18/4985", "text": "Dongmin Kim"}, {"@pid": "264/6394", "text": "Sumin Han"}, {"@pid": "119/3371", "text": "Heesuk Son"}, {"@pid": "89/81", "text": "Dongman Lee"}]}, "title": "Human Activity Recognition Using Semi-supervised Multi-modal DEC for Instagram Data.", "venue": "PAKDD", "pages": "869-880", "year": "2020", "type": "Conference and Workshop Papers", "access": "closed", "key": "conf/pakdd/KimHSL20", "doi": "10.1007/978-3-030-47426-3_67", "ee": "https://doi.org/10.1007/978-3-030-47426-3_67", "url": "https://dblp.org/rec/conf/pakdd/KimHSL20"}, "url": "URL#579786"}, {"@score": "1", "@id": "579790", "info": {"authors": {"author": [{"@pid": "247/6185", "text": "Bonhun Koo"}, {"@pid": "207/7677", "text": "Hyunsik Jeon"}, {"@pid": "13/7122", "text": "U Kang"}]}, "title": "Accurate News Recommendation Coalescing Personal and Global Temporal Preferences.", "venue": "PAKDD", "pages": "78-90", "year": "2020", "type": "Conference and Workshop Papers", "access": "closed", "key": "conf/pakdd/KooJK20", "doi": "10.1007/978-3-030-47426-3_7", "ee": "https://doi.org/10.1007/978-3-030-47426-3_7", "url": "https://dblp.org/rec/conf/pakdd/KooJK20"}, "url": "URL#579790"}, {"@score": "1", "@id": "579792", "info": {"authors": {"author": {"@pid": "137/9462", "text": "Jesse Laeuchli"}}, "title": "Fast Community Detection with Graph Sparsification.", "venue": "PAKDD", "pages": "291-304", "year": "2020", "type": "Conference and Workshop Papers", "access": "closed", "key": "conf/pakdd/Laeuchli20", "doi": "10.1007/978-3-030-47426-3_23", "ee": "https://doi.org/10.1007/978-3-030-47426-3_23", "url": "https://dblp.org/rec/conf/pakdd/Laeuchli20"}, "url": "URL#579792"}, {"@score": "1", "@id": "579796", "info": {"authors": {"author": [{"@pid": "66/3387", "text": "Hui Li"}, {"@pid": "66/3387", "text": "Hui Li"}, {"@pid": "b/SSBhowmick", "text": "Sourav S. Bhowmick"}]}, "title": "BRUNCH - Branching Structure Inference of Hybrid Multivariate Hawkes Processes with Application to Social Media.", "venue": "PAKDD", "pages": "553-566", "year": "2020", "type": "Conference and Workshop Papers", "access": "closed", "key": "conf/pakdd/LiLB20", "doi": "10.1007/978-3-030-47426-3_43", "ee": "https://doi.org/10.1007/978-3-030-47426-3_43", "url": "https://dblp.org/rec/conf/pakdd/LiLB20"}, "url": "URL#579796"}, {"@score": "1", "@id": "579797", "info": {"authors": {"author": [{"@pid": "37/4190", "text": "Yang Li"}, {"@pid": "182/2414", "text": "Yadan Luo"}, {"@pid": "70/6862", "text": "Zi Huang"}]}, "title": "Fashion Recommendation with Multi-relational Representation Learning.", "venue": "PAKDD", "pages": "3-15", "year": "2020", "type": "Conference and Workshop Papers", "access": "closed", "key": "conf/pakdd/LiLH20", "doi": "10.1007/978-3-030-47426-3_1", "ee": "https://doi.org/10.1007/978-3-030-47426-3_1", "url": "https://dblp.org/rec/conf/pakdd/LiLH20"}, "url": "URL#579797"}, {"@score": "1", "@id": "579798", "info": {"authors": {"author": [{"@pid": "51/3185", "text": "Wenbo Li"}, {"@pid": "95/8066", "text": "Tetsu Matsukawa"}, {"@pid": "12/898", "text": "Hiroto Saigo"}, {"@pid": "s/EinoshinSuzuki", "text": "Einoshin Suzuki"}]}, "title": "Context-Aware Latent Dirichlet Allocation for Topic Segmentation.", "venue": "PAKDD", "pages": "475-486", "year": "2020", "type": "Conference and Workshop Papers", "access": "closed", "key": "conf/pakdd/LiMSS20", "doi": "10.1007/978-3-030-47426-3_37", "ee": "https://doi.org/10.1007/978-3-030-47426-3_37", "url": "https://dblp.org/rec/conf/pakdd/LiMSS20"}, "url": "URL#579798"}, {"@score": "1", "@id": "579799", "info": {"authors": {"author": [{"@pid": "147/0314", "text": "Jiayu Li"}, {"@pid": "181/7386", "text": "Tianyun Zhang"}, {"@pid": "29/1374", "text": "Hao Tian"}, {"@pid": "207/9954", "text": "Shengmin Jin"}, {"@pid": "36/6214", "text": "Makan Fardad"}, {"@pid": "93/909", "text": "Reza Zafarani"}]}, "title": "SGCN - A Graph Sparsifier Based on Graph Convolutional Networks.", "venue": "PAKDD", "pages": "275-287", "year": "2020", "type": "Conference and Workshop Papers", "access": "closed", "key": "conf/pakdd/LiZTJFZ20", "doi": "10.1007/978-3-030-47426-3_22", "ee": "https://doi.org/10.1007/978-3-030-47426-3_22", "url": "https://dblp.org/rec/conf/pakdd/LiZTJFZ20"}, "url": "URL#579799"}, {"@score": "1", "@id": "579801", "info": {"authors": {"author": [{"@pid": "40/1491", "text": "Xiang Li"}, {"@pid": "69/4229", "text": "Xinning Zhu"}, {"@pid": "203/5219", "text": "Xiaoying Zhu"}, {"@pid": "72/1056-1", "text": "Yang Ji 0001"}, {"@pid": "120/8024", "text": "Xiaosheng Tang"}]}, "title": "Student Academic Performance Prediction Using Deep Multi-source Behavior Sequential Network.", "venue": "PAKDD", "pages": "567-579", "year": "2020", "type": "Conference and Workshop Papers", "access": "closed", "key": "conf/pakdd/LiZZJT20", "doi": "10.1007/978-3-030-47426-3_44", "ee": "https://doi.org/10.1007/978-3-030-47426-3_44", "url": "https://dblp.org/rec/conf/pakdd/LiZZJT20"}, "url": "URL#579801"}, {"@score": "1", "@id": "579804", "info": {"authors": {"author": [{"@pid": "75/2746", "text": "Weiwen Liu"}, {"@pid": "77/1318", "text": "Feng Liu"}, {"@pid": "24/10003", "text": "Ruiming Tang"}, {"@pid": "258/3778", "text": "Ben Liao"}, {"@pid": "175/1354", "text": "Guangyong Chen"}, {"@pid": "52/2889", "text": "Pheng-Ann Heng"}]}, "title": "Balancing Between Accuracy and Fairness for Interactive Recommendation with Reinforcement Learning.", "venue": "PAKDD", "pages": "155-167", "year": "2020", "type": "Conference and Workshop Papers", "access": "closed", "key": "conf/pakdd/LiuLTLCH20", "doi": "10.1007/978-3-030-47426-3_13", "ee": "https://doi.org/10.1007/978-3-030-47426-3_13", "url": "https://dblp.org/rec/conf/pakdd/LiuLTLCH20"}, "url": "URL#579804"}, {"@score": "1", "@id": "579807", "info": {"authors": {"author": [{"@pid": "245/2906", "text": "Vijaikumar M"}, {"@pid": "66/6214", "text": "Shirish K. Shevade"}, {"@pid": "m/MNarasimhaMurty", "text": "M. Narasimha Murty"}]}, "title": "GAMMA - A Graph and Multi-view Memory Attention Mechanism for Top-N Heterogeneous Recommendation.", "venue": "PAKDD", "pages": "28-40", "year": "2020", "type": "Conference and Workshop Papers", "access": "closed", "key": "conf/pakdd/MSM20", "doi": "10.1007/978-3-030-47426-3_3", "ee": "https://doi.org/10.1007/978-3-030-47426-3_3", "url": "https://dblp.org/rec/conf/pakdd/MSM20"}, "url": "URL#579807"}, {"@score": "1", "@id": "579808", "info": {"authors": {"author": [{"@pid": "221/2918", "text": "Jaron Mar"}, {"@pid": "46/4291", "text": "Jiamou Liu"}]}, "title": "What&apos;s in a Gist? Towards an Unsupervised Gist Representation for Few-Shot Large Document Classification.", "venue": "PAKDD", "pages": "261-274", "year": "2020", "type": "Conference and Workshop Papers", "access": "closed", "key": "conf/pakdd/MarL20", "doi": "10.1007/978-3-030-47426-3_21", "ee": "https://doi.org/10.1007/978-3-030-47426-3_21", "url": "https://dblp.org/rec/conf/pakdd/MarL20"}, "url": "URL#579808"}, {"@score": "1", "@id": "579813", "info": {"authors": {"author": [{"@pid": "130/0396", "text": "Alex Morales"}, {"@pid": "127/1202", "text": "Kanika Narang"}, {"@pid": "s/HariSundaram", "text": "Hari Sundaram"}, {"@pid": "z/ChengXiangZhai", "text": "Chengxiang Zhai"}]}, "title": "CrowdQM - Learning Aspect-Level User Reliability and Comment Trustworthiness in Discussion Forums.", "venue": "PAKDD", "pages": "592-605", "year": "2020", "type": "Conference and Workshop Papers", "access": "closed", "key": "conf/pakdd/MoralesNSZ20", "doi": "10.1007/978-3-030-47426-3_46", "ee": "https://doi.org/10.1007/978-3-030-47426-3_46", "url": "https://dblp.org/rec/conf/pakdd/MoralesNSZ20"}, "url": "URL#579813"}, {"@score": "1", "@id": "579815", "info": {"authors": {"author": [{"@pid": "94/5094", "text": "Van Nguyen"}, {"@pid": "88/8728", "text": "Trung Le"}, {"@pid": "245/4880", "text": "Tue Le"}, {"@pid": "53/6791", "text": "Khanh Nguyen"}, {"@pid": "06/3162", "text": "Olivier Y. de Vel"}, {"@pid": "50/805", "text": "Paul Montague"}, {"@pid": "g/JohnCGrundy", "text": "John C. Grundy"}, {"@pid": "71/5859", "text": "Dinh Phung 0001"}]}, "title": "Code Action Network for Binary Function Scope Identification.", "venue": "PAKDD", "pages": "712-725", "year": "2020", "type": "Conference and Workshop Papers", "access": "closed", "key": "conf/pakdd/NguyenLLNVMGP20", "doi": "10.1007/978-3-030-47426-3_55", "ee": "https://doi.org/10.1007/978-3-030-47426-3_55", "url": "https://dblp.org/rec/conf/pakdd/NguyenLLNVMGP20"}, "url": "URL#579815"}, {"@score": "1", "@id": "579818", "info": {"authors": {"author": [{"@pid": "94/5094", "text": "Van Nguyen"}, {"@pid": "88/8728", "text": "Trung Le"}, {"@pid": "06/3162", "text": "Olivier Y. de Vel"}, {"@pid": "50/805", "text": "Paul Montague"}, {"@pid": "g/JohnCGrundy", "text": "John C. Grundy"}, {"@pid": "71/5859", "text": "Dinh Phung 0001"}]}, "title": "Dual-Component Deep Domain Adaptation - A New Approach for Cross Project Software Vulnerability Detection.", "venue": "PAKDD", "pages": "699-711", "year": "2020", "type": "Conference and Workshop Papers", "access": "closed", "key": "conf/pakdd/NguyenLVMGP20", "doi": "10.1007/978-3-030-47426-3_54", "ee": "https://doi.org/10.1007/978-3-030-47426-3_54", "url": "https://dblp.org/rec/conf/pakdd/NguyenLVMGP20"}, "url": "URL#579818"}, {"@score": "1", "@id": "579819", "info": {"authors": {"author": [{"@pid": "146/9250", "text": "Shu-Chao Pang"}, {"@pid": "254/8233", "text": "AnAn Du"}, {"@pid": "126/5960", "text": "Zhenmei Yu"}, {"@pid": "o/MehmetAOrgun", "text": "Mehmet A. Orgun"}]}, "title": "Correlation Matters - Multi-scale Fine-Grained Contextual Information Extraction for Hepatic Tumor Segmentation.", "venue": "PAKDD", "pages": "462-474", "year": "2020", "type": "Conference and Workshop Papers", "access": "closed", "key": "conf/pakdd/PangDYO20", "doi": "10.1007/978-3-030-47426-3_36", "ee": "https://doi.org/10.1007/978-3-030-47426-3_36", "url": "https://dblp.org/rec/conf/pakdd/PangDYO20"}, "url": "URL#579819"}, {"@score": "1", "@id": "579820", "info": {"authors": {"author": [{"@pid": "177/1808", "text": "Dimitris Paraschakis"}, {"@pid": "62/3977", "text": "Bengt J. Nilsson"}]}, "title": "FlowRec - Prototyping Session-Based Recommender Systems in Streaming Mode.", "venue": "PAKDD", "pages": "65-77", "year": "2020", "type": "Conference and Workshop Papers", "access": "closed", "key": "conf/pakdd/ParaschakisN20", "doi": "10.1007/978-3-030-47426-3_6", "ee": "https://doi.org/10.1007/978-3-030-47426-3_6", "url": "https://dblp.org/rec/conf/pakdd/ParaschakisN20"}, "url": "URL#579820"}, {"@score": "1", "@id": "579823", "info": {"authors": {"author": [{"@pid": "27/10105", "text": "Kushani Perera"}, {"@pid": "19/3414", "text": "Jeffrey Chan"}, {"@pid": "47/5584", "text": "Shanika Karunasekera"}]}, "title": "A Framework for Feature Selection to Exploit Feature Group Structures.", "venue": "PAKDD", "pages": "792-804", "year": "2020", "type": "Conference and Workshop Papers", "access": "closed", "key": "conf/pakdd/PereraCK20", "doi": "10.1007/978-3-030-47426-3_61", "ee": "https://doi.org/10.1007/978-3-030-47426-3_61", "url": "https://dblp.org/rec/conf/pakdd/PereraCK20"}, "url": "URL#579823"}, {"@score": "1", "@id": "579824", "info": {"authors": {"author": [{"@pid": "27/10105", "text": "Kushani Perera"}, {"@pid": "19/3414", "text": "Jeffrey Chan"}, {"@pid": "47/5584", "text": "Shanika Karunasekera"}]}, "title": "Group Based Unsupervised Feature Selection.", "venue": "PAKDD", "pages": "805-817", "year": "2020", "type": "Conference and Workshop Papers", "access": "closed", "key": "conf/pakdd/PereraCK20a", "doi": "10.1007/978-3-030-47426-3_62", "ee": "https://doi.org/10.1007/978-3-030-47426-3_62", "url": "https://dblp.org/rec/conf/pakdd/PereraCK20a"}, "url": "URL#579824"}, {"@score": "1", "@id": "579829", "info": {"authors": {"author": [{"@pid": "264/6381", "text": "Aman Roy"}, {"@pid": "222/3178", "text": "Vinayak Kumar"}, {"@pid": "29/2804", "text": "Debdoot Mukherjee"}, {"@pid": "65/2136-2", "text": "Tanmoy Chakraborty 0002"}]}, "title": "Learning Multigraph Node Embeddings Using Guided L\u00e9vy Flights.", "venue": "PAKDD", "pages": "524-537", "year": "2020", "type": "Conference and Workshop Papers", "access": "closed", "key": "conf/pakdd/RoyKMC20", "doi": "10.1007/978-3-030-47426-3_41", "ee": "https://doi.org/10.1007/978-3-030-47426-3_41", "url": "https://dblp.org/rec/conf/pakdd/RoyKMC20"}, "url": "URL#579829"}, {"@score": "1", "@id": "579830", "info": {"authors": {"author": [{"@pid": "168/2466", "text": "Puloma Roy"}, {"@pid": "77/3092", "text": "Sadia Sharmin"}, {"@pid": "70/4449", "text": "Amin Ahsan Ali"}, {"@pid": "66/5059", "text": "Mohammad Shoyaib"}]}, "title": "Discretization and Feature Selection Based on Bias Corrected Mutual Information Considering High-Order Dependencies.", "venue": "PAKDD", "pages": "830-842", "year": "2020", "type": "Conference and Workshop Papers", "access": "closed", "key": "conf/pakdd/RoySAS20", "doi": "10.1007/978-3-030-47426-3_64", "ee": "https://doi.org/10.1007/978-3-030-47426-3_64", "url": "https://dblp.org/rec/conf/pakdd/RoySAS20"}, "url": "URL#579830"}, {"@score": "1", "@id": "579832", "info": {"authors": {"author": [{"@pid": "208/2319", "text": "Xuewen Shi"}, {"@pid": "27/8686", "text": "Heyan Huang"}, {"@pid": "64/8451", "text": "Ping Jian"}, {"@pid": "188/7122", "text": "Yi-Kun Tang"}]}, "title": "Case-Sensitive Neural Machine Translation.", "venue": "PAKDD", "pages": "662-674", "year": "2020", "type": "Conference and Workshop Papers", "access": "closed", "key": "conf/pakdd/ShiHJT20", "doi": "10.1007/978-3-030-47426-3_51", "ee": "https://doi.org/10.1007/978-3-030-47426-3_51", "url": "https://dblp.org/rec/conf/pakdd/ShiHJT20"}, "url": "URL#579832"}, {"@score": "1", "@id": "579835", "info": {"authors": {"author": [{"@pid": "171/2240", "text": "Amira Soliman 0001"}, {"@pid": "42/3994", "text": "Sarunas Girdzijauskas"}, {"@pid": "23/10872", "text": "Mohamed-Rafik Bouguelia"}, {"@pid": "72/4007", "text": "Sepideh Pashami"}, {"@pid": "33/4548", "text": "Slawomir Nowaczyk"}]}, "title": "Decentralized and Adaptive K-Means Clustering for Non-IID Data Using HyperLogLog Counters.", "venue": "PAKDD", "pages": "343-355", "year": "2020", "type": "Conference and Workshop Papers", "access": "closed", "key": "conf/pakdd/SolimanGBPN20", "doi": "10.1007/978-3-030-47426-3_27", "ee": "https://doi.org/10.1007/978-3-030-47426-3_27", "url": "https://dblp.org/rec/conf/pakdd/SolimanGBPN20"}, "url": "URL#579835"}, {"@score": "1", "@id": "579837", "info": {"authors": {"author": [{"@pid": "264/6404", "text": "Chunyang Tan"}, {"@pid": "238/4159", "text": "Kaijia Yang"}, {"@pid": "39/5815", "text": "Xinyu Dai"}, {"@pid": "57/8451", "text": "Shujian Huang"}, {"@pid": "42/4315", "text": "Jiajun Chen"}]}, "title": "MSGE - A Multi-step Gated Model for Knowledge Graph Completion.", "venue": "PAKDD", "pages": "424-435", "year": "2020", "type": "Conference and Workshop Papers", "access": "closed", "key": "conf/pakdd/TanYDHC20", "doi": "10.1007/978-3-030-47426-3_33", "ee": "https://doi.org/10.1007/978-3-030-47426-3_33", "url": "https://dblp.org/rec/conf/pakdd/TanYDHC20"}, "url": "URL#579837"}, {"@score": "1", "@id": "579838", "info": {"authors": {"author": [{"@pid": "261/9705", "text": "Hengzhu Tang"}, {"@pid": "97/5152", "text": "Yanan Cao"}, {"@pid": "01/1844-6", "text": "Zhenyu Zhang 0006"}, {"@pid": "261/9841", "text": "Jiangxia Cao"}, {"@pid": "74/3719-9", "text": "Fang Fang 0009"}, {"@pid": "55/2449", "text": "Shi Wang"}, {"@pid": "97/8996", "text": "Pengfei Yin"}]}, "title": "HIN - Hierarchical Inference Network for Document-Level Relation Extraction.", "venue": "PAKDD", "pages": "197-209", "year": "2020", "type": "Conference and Workshop Papers", "access": "closed", "key": "conf/pakdd/TangC0CFWY20", "doi": "10.1007/978-3-030-47426-3_16", "ee": "https://doi.org/10.1007/978-3-030-47426-3_16", "url": "https://dblp.org/rec/conf/pakdd/TangC0CFWY20"}, "url": "URL#579838"}, {"@score": "1", "@id": "579840", "info": {"authors": {"author": {"@pid": "02/5889", "text": "Yu Wang"}}, "title": "A Hybrid Recommendation for Music Based on Reinforcement Learning.", "venue": "PAKDD", "pages": "91-103", "year": "2020", "type": "Conference and Workshop Papers", "access": "closed", "key": "conf/pakdd/Wang20", "doi": "10.1007/978-3-030-47426-3_8", "ee": "https://doi.org/10.1007/978-3-030-47426-3_8", "url": "https://dblp.org/rec/conf/pakdd/Wang20"}, "url": "URL#579840"}, {"@score": "1", "@id": "579841", "info": {"authors": {"author": [{"@pid": "07/1021", "text": "Xiaodong Wang"}, {"@pid": "77/35", "text": "Zhen Liu"}, {"@pid": "33/10340", "text": "Nana Wang"}, {"@pid": "18/7544", "text": "Wentao Fan"}]}, "title": "Relational Metric Learning with Dual Graph Attention Networks for Social Recommendation.", "venue": "PAKDD", "pages": "104-117", "year": "2020", "type": "Conference and Workshop Papers", "access": "closed", "key": "conf/pakdd/WangLWF20", "doi": "10.1007/978-3-030-47426-3_9", "ee": "https://doi.org/10.1007/978-3-030-47426-3_9", "url": "https://dblp.org/rec/conf/pakdd/WangLWF20"}, "url": "URL#579841"}, {"@score": "1", "@id": "579842", "info": {"authors": {"author": [{"@pid": "264/6399", "text": "Xiangmeng Wang"}, {"@pid": "69/5902-6", "text": "Qian Li 0006"}, {"@pid": "78/570", "text": "Wu Zhang"}, {"@pid": "59/2340", "text": "Guandong Xu"}, {"@pid": "115/5163", "text": "Shaowu Liu"}, {"@pid": "90/7062", "text": "Wenhao Zhu"}]}, "title": "Joint Relational Dependency Learning for Sequential Recommendation.", "venue": "PAKDD", "pages": "168-180", "year": "2020", "type": "Conference and Workshop Papers", "access": "closed", "key": "conf/pakdd/WangLZXLZ20", "doi": "10.1007/978-3-030-47426-3_14", "ee": "https://doi.org/10.1007/978-3-030-47426-3_14", "url": "https://dblp.org/rec/conf/pakdd/WangLZXLZ20"}, "url": "URL#579842"}, {"@score": "1", "@id": "579843", "info": {"authors": {"author": [{"@pid": "181/2812", "text": "Hao Wang"}, {"@pid": "98/917", "text": "Huawei Shen"}, {"@pid": "44/912", "text": "Xueqi Cheng"}]}, "title": "Modeling Users&apos; Multifaceted Interest Correlation for Social Recommendation.", "venue": "PAKDD", "pages": "118-129", "year": "2020", "type": "Conference and Workshop Papers", "access": "closed", "key": "conf/pakdd/WangSC20", "doi": "10.1007/978-3-030-47426-3_10", "ee": "https://doi.org/10.1007/978-3-030-47426-3_10", "url": "https://dblp.org/rec/conf/pakdd/WangSC20"}, "url": "URL#579843"}, {"@score": "1", "@id": "579844", "info": {"authors": {"author": [{"@pid": "181/2812", "text": "Hao Wang"}, {"@pid": "98/917", "text": "Huawei Shen"}, {"@pid": "44/912", "text": "Xueqi Cheng"}]}, "title": "Modeling POI-Specific Spatial-Temporal Context for Point-of-Interest Recommendation.", "venue": "PAKDD", "pages": "130-141", "year": "2020", "type": "Conference and Workshop Papers", "access": "closed", "key": "conf/pakdd/WangSC20a", "doi": "10.1007/978-3-030-47426-3_11", "ee": "https://doi.org/10.1007/978-3-030-47426-3_11", "url": "https://dblp.org/rec/conf/pakdd/WangSC20a"}, "url": "URL#579844"}, {"@score": "1", "@id": "579845", "info": {"authors": {"author": [{"@pid": "59/10537", "text": "Xianjing Wang"}, {"@pid": "08/1554", "text": "Flora D. Salim"}, {"@pid": "58/6608", "text": "Yongli Ren"}, {"@pid": "25/8616", "text": "Piotr Koniusz"}]}, "title": "Relation Embedding for Personalised Translation-Based POI Recommendation.", "venue": "PAKDD", "pages": "53-64", "year": "2020", "type": "Conference and Workshop Papers", "access": "closed", "key": "conf/pakdd/WangSRK20", "doi": "10.1007/978-3-030-47426-3_5", "ee": "https://doi.org/10.1007/978-3-030-47426-3_5", "url": "https://dblp.org/rec/conf/pakdd/WangSRK20"}, "url": "URL#579845"}, {"@score": "1", "@id": "579846", "info": {"authors": {"author": [{"@pid": "36/5574-2", "text": "Xuesong Wang 0002"}, {"@pid": "56/6651", "text": "Lina Yao"}, {"@pid": "49/3283-101", "text": "Wei Liu 0101"}, {"@pid": "94/10021", "text": "Can Li"}, {"@pid": "119/1223-1", "text": "Lei Bai 0001"}, {"@pid": "55/4916", "text": "S. Travis Waller"}]}, "title": "Mobility Irregularity Detection with Smart Transit Card Data.", "venue": "PAKDD", "pages": "541-552", "year": "2020", "type": "Conference and Workshop Papers", "access": "closed", "key": "conf/pakdd/WangYLLBW20", "doi": "10.1007/978-3-030-47426-3_42", "ee": "https://doi.org/10.1007/978-3-030-47426-3_42", "url": "https://dblp.org/rec/conf/pakdd/WangYLLBW20"}, "url": "URL#579846"}, {"@score": "1", "@id": "579847", "info": {"authors": {"author": [{"@pid": "78/1760", "text": "Chengwei Wang"}, {"@pid": "133/7750", "text": "Tengfei Zhou"}, {"@pid": "65/4423-43", "text": "Chen Chen 0043"}, {"@pid": "02/3803", "text": "Tianlei Hu"}, {"@pid": "67/6383-1", "text": "Gang Chen 0001"}]}, "title": "Off-Policy Recommendation System Without Exploration.", "venue": "PAKDD", "pages": "16-27", "year": "2020", "type": "Conference and Workshop Papers", "access": "closed", "key": "conf/pakdd/WangZ0HC20", "doi": "10.1007/978-3-030-47426-3_2", "ee": "https://doi.org/10.1007/978-3-030-47426-3_2", "url": "https://dblp.org/rec/conf/pakdd/WangZ0HC20"}, "url": "URL#579847"}, {"@score": "1", "@id": "579848", "info": {"authors": {"author": [{"@pid": "66/2157", "text": "Yubin Wang"}, {"@pid": "01/1844-6", "text": "Zhenyu Zhang 0006"}, {"@pid": "56/7911", "text": "Tingwen Liu"}, {"@pid": "02/929-1", "text": "Li Guo 0001"}]}, "title": "SLGAT - Soft Labels Guided Graph Attention Networks.", "venue": "PAKDD", "pages": "512-523", "year": "2020", "type": "Conference and Workshop Papers", "access": "closed", "key": "conf/pakdd/WangZLG20", "doi": "10.1007/978-3-030-47426-3_40", "ee": "https://doi.org/10.1007/978-3-030-47426-3_40", "url": "https://dblp.org/rec/conf/pakdd/WangZLG20"}, "url": "URL#579848"}, {"@score": "1", "@id": "579851", "info": {"authors": {"author": [{"@pid": "33/4236", "text": "Wenbin Wu"}, {"@pid": "36/5558-1", "text": "Tong Liu 0001"}, {"@pid": "219/8474", "text": "Jiahao Yang"}]}, "title": "CACRNN - A Context-Aware Attention-Based Convolutional Recurrent Neural Network for Fine-Grained Taxi Demand Prediction.", "venue": "PAKDD", "pages": "636-648", "year": "2020", "type": "Conference and Workshop Papers", "access": "closed", "key": "conf/pakdd/Wu0Y20", "doi": "10.1007/978-3-030-47426-3_49", "ee": "https://doi.org/10.1007/978-3-030-47426-3_49", "url": "https://dblp.org/rec/conf/pakdd/Wu0Y20"}, "url": "URL#579851"}, {"@score": "1", "@id": "579852", "info": {"authors": {"author": [{"@pid": "75/5056", "text": "Tong Wu"}, {"@pid": "48/1091", "text": "Yiqiang Chen"}, {"@pid": "01/5858", "text": "Yang Gu"}, {"@pid": "35/6656", "text": "Jiwei Wang"}, {"@pid": "140/7295", "text": "Siyu Zhang"}, {"@pid": "264/6388", "text": "Zhanghu Zhechen"}]}, "title": "Multi-Layer Cross Loss Model for Zero-Shot Human Activity Recognition.", "venue": "PAKDD", "pages": "210-221", "year": "2020", "type": "Conference and Workshop Papers", "access": "closed", "key": "conf/pakdd/WuCGWZZ20", "doi": "10.1007/978-3-030-47426-3_17", "ee": "https://doi.org/10.1007/978-3-030-47426-3_17", "url": "https://dblp.org/rec/conf/pakdd/WuCGWZZ20"}, "url": "URL#579852"}, {"@score": "1", "@id": "579854", "info": {"authors": {"author": [{"@pid": "82/7635", "text": "Zhifeng Xie"}, {"@pid": "86/4025", "text": "Wenling Zhang"}, {"@pid": "42/9423", "text": "Huiming Ding"}, {"@pid": "10/4950", "text": "Lizhuang Ma"}]}, "title": "MsFcNET - Multi-scale Feature-Crossing Attention Network for Multi-field Sparse Data.", "venue": "PAKDD", "pages": "142-154", "year": "2020", "type": "Conference and Workshop Papers", "access": "closed", "key": "conf/pakdd/XieZDM20", "doi": "10.1007/978-3-030-47426-3_12", "ee": "https://doi.org/10.1007/978-3-030-47426-3_12", "url": "https://dblp.org/rec/conf/pakdd/XieZDM20"}, "url": "URL#579854"}, {"@score": "1", "@id": "579858", "info": {"authors": {"author": [{"@pid": "63/4117", "text": "Jianyu Zhang"}, {"@pid": "21/7664", "text": "Jianye Hao"}, {"@pid": "07/5814", "text": "Fran\u00e7oise Fogelman-Souli\u00e9"}]}, "title": "Cross-data Automatic Feature Engineering via Meta-learning and Reinforcement Learning.", "venue": "PAKDD", "pages": "818-829", "year": "2020", "type": "Conference and Workshop Papers", "access": "closed", "key": "conf/pakdd/ZhangHF20", "doi": "10.1007/978-3-030-47426-3_63", "ee": "https://doi.org/10.1007/978-3-030-47426-3_63", "url": "https://dblp.org/rec/conf/pakdd/ZhangHF20"}, "url": "URL#579858"}, {"@score": "1", "@id": "579860", "info": {"authors": {"author": [{"@pid": "141/4448", "text": "Yuanzhe Zhang"}, {"@pid": "00/1811", "text": "Ling Luo"}, {"@pid": "181/2842", "text": "Yang Wang"}, {"@pid": "62/234", "text": "Zhiyong Wang"}]}, "title": "FCP Filter - A Dynamic Clustering-Prediction Framework for Customer Behavior.", "venue": "PAKDD", "pages": "580-591", "year": "2020", "type": "Conference and Workshop Papers", "access": "closed", "key": "conf/pakdd/ZhangLWW20", "doi": "10.1007/978-3-030-47426-3_45", "ee": "https://doi.org/10.1007/978-3-030-47426-3_45", "url": "https://dblp.org/rec/conf/pakdd/ZhangLWW20"}, "url": "URL#579860"}, {"@score": "1", "@id": "579862", "info": {"authors": {"author": [{"@pid": "24/2058", "text": "He Zhang"}, {"@pid": "68/8371", "text": "Fran\u00e7ois Petitjean"}, {"@pid": "72/3885", "text": "Wray L. Buntine"}]}, "title": "Hierarchical Gradient Smoothing for Probability Estimation Trees.", "venue": "PAKDD", "pages": "222-234", "year": "2020", "type": "Conference and Workshop Papers", "access": "closed", "key": "conf/pakdd/ZhangPB20", "doi": "10.1007/978-3-030-47426-3_18", "ee": "https://doi.org/10.1007/978-3-030-47426-3_18", "url": "https://dblp.org/rec/conf/pakdd/ZhangPB20"}, "url": "URL#579862"}, {"@score": "1", "@id": "579863", "info": {"authors": {"author": [{"@pid": "40/4372", "text": "Xianchao Zhang"}, {"@pid": "250/1158", "text": "Xiaorui Tang"}, {"@pid": "160/3158", "text": "Linlin Zong"}, {"@pid": "45/2337", "text": "Xinyue Liu"}, {"@pid": "264/6405", "text": "Jie Mu"}]}, "title": "Deep Multimodal Clustering with Cross Reconstruction.", "venue": "PAKDD", "pages": "305-317", "year": "2020", "type": "Conference and Workshop Papers", "access": "closed", "key": "conf/pakdd/ZhangTZLM20", "doi": "10.1007/978-3-030-47426-3_24", "ee": "https://doi.org/10.1007/978-3-030-47426-3_24", "url": "https://dblp.org/rec/conf/pakdd/ZhangTZLM20"}, "url": "URL#579863"}, {"@score": "1", "@id": "579869", "info": {"authors": {"author": [{"@pid": "98/4450", "text": "Tao Zhou"}, {"@pid": "l/EePengLim", "text": "Ee-Peng Lim"}, {"@pid": "139/2266", "text": "Roy Ka-Wei Lee"}, {"@pid": "77/1985", "text": "Feida Zhu 0001"}, {"@pid": "20/2389", "text": "Jiuxin Cao"}]}, "title": "Retrofitting Embeddings for Unsupervised User Identity Linkage.", "venue": "PAKDD", "pages": "385-397", "year": "2020", "type": "Conference and Workshop Papers", "access": "closed", "key": "conf/pakdd/ZhouLL0C20", "doi": "10.1007/978-3-030-47426-3_30", "ee": "https://doi.org/10.1007/978-3-030-47426-3_30", "url": "https://dblp.org/rec/conf/pakdd/ZhouLL0C20"}, "url": "URL#579869"}, {"@score": "1", "@id": "579870", "info": {"authors": {"author": [{"@pid": "05/3403", "text": "Xin Zhou"}, {"@pid": "163/5129", "text": "Zhu Sun"}, {"@pid": "84/10716", "text": "Guibing Guo"}, {"@pid": "87/2948", "text": "Yuan Liu"}]}, "title": "Modelling Temporal Dynamics and Repeated Behaviors for Recommendation.", "venue": "PAKDD", "pages": "181-193", "year": "2020", "type": "Conference and Workshop Papers", "access": "closed", "key": "conf/pakdd/ZhouSGL20", "doi": "10.1007/978-3-030-47426-3_15", "ee": "https://doi.org/10.1007/978-3-030-47426-3_15", "url": "https://dblp.org/rec/conf/pakdd/ZhouSGL20"}, "url": "URL#579870"}, {"@score": "1", "@id": "579873", "info": {"authors": {"author": [{"@pid": "98/4450", "text": "Tao Zhou"}, {"@pid": "73/7697", "text": "Yuxiang Zhang"}, {"@pid": "192/9127", "text": "Haoxiang Zhu"}]}, "title": "Multi-level Memory Network with CRFs for Keyphrase Extraction.", "venue": "PAKDD", "pages": "726-738", "year": "2020", "type": "Conference and Workshop Papers", "access": "closed", "key": "conf/pakdd/ZhouZZ20", "doi": "10.1007/978-3-030-47426-3_56", "ee": "https://doi.org/10.1007/978-3-030-47426-3_56", "url": "https://dblp.org/rec/conf/pakdd/ZhouZZ20"}, "url": "URL#579873"}, {"@score": "1", "@id": "579875", "info": {"authors": {"author": [{"@pid": "161/2889", "text": "Guanghui Zhu"}, {"@pid": "264/6377", "text": "Ruancheng Zhu"}]}, "title": "Accelerating Hyperparameter Optimization of Deep Neural Network via Progressive Multi-Fidelity Evaluation.", "venue": "PAKDD", "pages": "752-763", "year": "2020", "type": "Conference and Workshop Papers", "access": "closed", "key": "conf/pakdd/ZhuZ20", "doi": "10.1007/978-3-030-47426-3_58", "ee": "https://doi.org/10.1007/978-3-030-47426-3_58", "url": "https://dblp.org/rec/conf/pakdd/ZhuZ20"}, "url": "URL#579875"}, {"@score": "1", "@id": "611215", "info": {"authors": {"author": [{"@pid": "00/2494", "text": "Hady W. Lauw"}, {"@pid": "w/RaymondChiWingWong", "text": "Raymond Chi-Wing Wong"}, {"@pid": "92/2820", "text": "Alexandros Ntoulas"}, {"@pid": "l/EePengLim", "text": "Ee-Peng Lim"}, {"@pid": "00/5480", "text": "See-Kiong Ng"}, {"@pid": "80/5412", "text": "Sinno Jialin Pan"}]}, "title": "Advances in Knowledge Discovery and Data Mining - 24th Pacific-Asia Conference, PAKDD 2020, Singapore, May 11-14, 2020, Proceedings, Part I", "venue": ["PAKDD", "Lecture Notes in Computer Science"], "volume": "12084", "publisher": "Springer", "year": "2020", "type": "Editorship", "key": "conf/pakdd/2020-1", "doi": "10.1007/978-3-030-47426-3", "ee": "https://doi.org/10.1007/978-3-030-47426-3", "url": "https://dblp.org/rec/conf/pakdd/2020-1"}, "url": "URL#611215"}]}}}