{"result": {"query": ":facetid:toc:\"db/conf/pkdd/pkdd2019-1.bht\"", "status": {"@code": "200", "text": "OK"}, "time": {"@unit": "msecs", "text": "143.50"}, "completions": {"@total": "1", "@computed": "1", "@sent": "1", "c": {"@sc": "44", "@dc": "44", "@oc": "44", "@id": "31667885", "text": ":facetid:toc:db/conf/pkdd/pkdd2019-1.bht"}}, "hits": {"@total": "44", "@computed": "44", "@sent": "44", "@first": "0", "hit": [{"@score": "1", "@id": "611242", "info": {"authors": {"author": [{"@pid": "99/122", "text": "Ulf Brefeld"}, {"@pid": "06/5764", "text": "\u00c9lisa Fromont"}, {"@pid": "h/AndreasHotho", "text": "Andreas Hotho"}, {"@pid": "65/3461", "text": "Arno J. Knobbe"}, {"@pid": "06/9509", "text": "Marloes H. Maathuis"}, {"@pid": "r/CRobardet", "text": "C\u00e9line Robardet"}]}, "title": "Machine Learning and Knowledge Discovery in Databases - European Conference, ECML PKDD 2019, W\u00fcrzburg, Germany, September 16-20, 2019, Proceedings, Part I", "venue": ["ECML/PKDD", "Lecture Notes in Computer Science"], "volume": "11906", "publisher": "Springer", "year": "2020", "type": "Editorship", "key": "conf/pkdd/2019-1", "doi": "10.1007/978-3-030-46150-8", "ee": "https://doi.org/10.1007/978-3-030-46150-8", "url": "https://dblp.org/rec/conf/pkdd/2019-1"}, "url": "URL#611242"}, {"@score": "1", "@id": "994568", "info": {"authors": {"author": [{"@pid": "26/1137-1", "text": "Lu Bai 0001"}, {"@pid": "199/5814-1", "text": "Yuhang Jiao 0001"}, {"@pid": "72/5436", "text": "Lixin Cui"}, {"@pid": "h/EdwinRHancock", "text": "Edwin R. Hancock"}]}, "title": "Learning Aligned-Spatial Graph Convolutional Networks for Graph Classification.", "venue": "ECML/PKDD", "pages": "464-482", "year": "2019", "type": "Conference and Workshop Papers", "access": "closed", "key": "conf/pkdd/00010CH19", "doi": "10.1007/978-3-030-46150-8_28", "ee": "https://doi.org/10.1007/978-3-030-46150-8_28", "url": "https://dblp.org/rec/conf/pkdd/00010CH19"}, "url": "URL#994568"}, {"@score": "1", "@id": "994569", "info": {"authors": {"author": [{"@pid": "14/9077-1", "text": "Pedro Mercado 0001"}, {"@pid": "141/4817", "text": "Jessica Bosch"}, {"@pid": "17/8097", "text": "Martin Stoll"}]}, "title": "Node Classification for Signed Social Networks Using Diffuse Interface Methods.", "venue": "ECML/PKDD", "pages": "524-540", "year": "2019", "type": "Conference and Workshop Papers", "access": "closed", "key": "conf/pkdd/0001BS19", "doi": "10.1007/978-3-030-46150-8_31", "ee": "https://doi.org/10.1007/978-3-030-46150-8_31", "url": "https://dblp.org/rec/conf/pkdd/0001BS19"}, "url": "URL#994569"}, {"@score": "1", "@id": "994570", "info": {"authors": {"author": [{"@pid": "11/495-1", "text": "Giulia Bernardini 0001"}, {"@pid": "23/2916", "text": "Huiping Chen"}, {"@pid": "164/5849", "text": "Alessio Conte"}, {"@pid": "g/RobertoGrossi", "text": "Roberto Grossi"}, {"@pid": "96/4724", "text": "Grigorios Loukides"}, {"@pid": "p/NadiaPisanti", "text": "Nadia Pisanti"}, {"@pid": "89/7966", "text": "Solon P. Pissis"}, {"@pid": "14/4683", "text": "Giovanna Rosone"}]}, "title": "String Sanitization - A Combinatorial Approach.", "venue": "ECML/PKDD", "pages": "627-644", "year": "2019", "type": "Conference and Workshop Papers", "access": "closed", "key": "conf/pkdd/0001CCGLPPR19", "doi": "10.1007/978-3-030-46150-8_37", "ee": "https://doi.org/10.1007/978-3-030-46150-8_37", "url": "https://dblp.org/rec/conf/pkdd/0001CCGLPPR19"}, "url": "URL#994570"}, {"@score": "1", "@id": "994577", "info": {"authors": {"author": [{"@pid": "199/6349", "text": "Ghadeer Abuoda"}, {"@pid": "53/7323", "text": "Gianmarco De Francisci Morales"}, {"@pid": "01/3996", "text": "Ashraf Aboulnaga"}]}, "title": "Link Prediction via Higher-Order Motif Features.", "venue": "ECML/PKDD", "pages": "412-429", "year": "2019", "type": "Conference and Workshop Papers", "access": "closed", "key": "conf/pkdd/AbuodaMA19", "doi": "10.1007/978-3-030-46150-8_25", "ee": "https://doi.org/10.1007/978-3-030-46150-8_25", "url": "https://dblp.org/rec/conf/pkdd/AbuodaMA19"}, "url": "URL#994577"}, {"@score": "1", "@id": "994596", "info": {"authors": {"author": [{"@pid": "264/0338", "text": "Mehran Hossein Zadeh Bazargani"}, {"@pid": "83/5307", "text": "Brian Mac Namee"}]}, "title": "The Elliptical Basis Function Data Descriptor (EBFDD) Network - A One-Class Classification Approach to Anomaly Detection.", "venue": "ECML/PKDD", "pages": "107-123", "year": "2019", "type": "Conference and Workshop Papers", "access": "closed", "key": "conf/pkdd/BazarganiN19", "doi": "10.1007/978-3-030-46150-8_7", "ee": "https://doi.org/10.1007/978-3-030-46150-8_7", "url": "https://dblp.org/rec/conf/pkdd/BazarganiN19"}, "url": "URL#994596"}, {"@score": "1", "@id": "994597", "info": {"authors": {"author": [{"@pid": "234/7839", "text": "Laura Beggel"}, {"@pid": "51/6791-1", "text": "Michael Pfeiffer 0001"}, {"@pid": "48/5326", "text": "Bernd Bischl"}]}, "title": "Robust Anomaly Detection in Images Using Adversarial Autoencoders.", "venue": "ECML/PKDD", "pages": "206-222", "year": "2019", "type": "Conference and Workshop Papers", "access": "closed", "key": "conf/pkdd/Beggel0B19", "doi": "10.1007/978-3-030-46150-8_13", "ee": "https://doi.org/10.1007/978-3-030-46150-8_13", "url": "https://dblp.org/rec/conf/pkdd/Beggel0B19"}, "url": "URL#994597"}, {"@score": "1", "@id": "994599", "info": {"authors": {"author": [{"@pid": "211/5742", "text": "Adnene Belfodil"}, {"@pid": "23/1341", "text": "Wouter Duivesteijn"}, {"@pid": "46/2965", "text": "Marc Plantevit"}, {"@pid": "53/6030", "text": "Sylvie Cazalens"}, {"@pid": "59/5146", "text": "Philippe Lamarre"}]}, "title": "DEvIANT - Discovering Significant Exceptional (Dis-)Agreement Within Groups.", "venue": "ECML/PKDD", "pages": "3-20", "year": "2019", "type": "Conference and Workshop Papers", "access": "closed", "key": "conf/pkdd/BelfodilDPCL19", "doi": "10.1007/978-3-030-46150-8_1", "ee": "https://doi.org/10.1007/978-3-030-46150-8_1", "url": "https://dblp.org/rec/conf/pkdd/BelfodilDPCL19"}, "url": "URL#994599"}, {"@score": "1", "@id": "994601", "info": {"authors": {"author": [{"@pid": "229/6164", "text": "Victor Berger"}, {"@pid": "s/MicheleSebag", "text": "Mich\u00e8le Sebag"}]}, "title": "From Abstract Items to Latent Spaces to Observed Data and Back - Compositional Variational Auto-Encoder.", "venue": "ECML/PKDD", "pages": "274-289", "year": "2019", "type": "Conference and Workshop Papers", "access": "closed", "key": "conf/pkdd/BergerS19", "doi": "10.1007/978-3-030-46150-8_17", "ee": "https://doi.org/10.1007/978-3-030-46150-8_17", "url": "https://dblp.org/rec/conf/pkdd/BergerS19"}, "url": "URL#994601"}, {"@score": "1", "@id": "994633", "info": {"authors": {"author": [{"@pid": "173/9119", "text": "Sarah Cooney"}, {"@pid": "78/2022-40", "text": "Kai Wang 0040"}, {"@pid": "207/0880", "text": "Elizabeth Bondi"}, {"@pid": "117/4935", "text": "Thanh Hong Nguyen"}, {"@pid": "08/3904", "text": "Phebe Vayanos"}, {"@pid": "160/9964", "text": "Hailey Winetrobe"}, {"@pid": "176/9310", "text": "Edward A. Cranford"}, {"@pid": "39/3618", "text": "Cleotilde Gonzalez"}, {"@pid": "57/241", "text": "Christian Lebiere"}, {"@pid": "67/2667", "text": "Milind Tambe"}]}, "title": "Learning to Signal in the Goldilocks Zone - Improving Adversary Compliance in Security Games.", "venue": "ECML/PKDD", "pages": "725-740", "year": "2019", "type": "Conference and Workshop Papers", "access": "closed", "key": "conf/pkdd/CooneyWBNVWCGLT19", "doi": "10.1007/978-3-030-46150-8_42", "ee": "https://doi.org/10.1007/978-3-030-46150-8_42", "url": "https://dblp.org/rec/conf/pkdd/CooneyWBNVWCGLT19"}, "url": "URL#994633"}, {"@score": "1", "@id": "994641", "info": {"authors": {"author": [{"@pid": "67/10405", "text": "Vachik S. Dave"}, {"@pid": "87/5931", "text": "Mohammad Al Hasan"}]}, "title": "Triangle Completion Time Prediction Using Time-Conserving Embedding.", "venue": "ECML/PKDD", "pages": "541-557", "year": "2019", "type": "Conference and Workshop Papers", "access": "closed", "key": "conf/pkdd/DaveH19", "doi": "10.1007/978-3-030-46150-8_32", "ee": "https://doi.org/10.1007/978-3-030-46150-8_32", "url": "https://dblp.org/rec/conf/pkdd/DaveH19"}, "url": "URL#994641"}, {"@score": "1", "@id": "994645", "info": {"authors": {"author": [{"@pid": "257/5046", "text": "Laurens Devos"}, {"@pid": "82/334", "text": "Wannes Meert"}, {"@pid": "d/JesseDavis", "text": "Jesse Davis"}]}, "title": "Fast Gradient Boosting Decision Trees with Bit-Level Data Structures.", "venue": "ECML/PKDD", "pages": "590-606", "year": "2019", "type": "Conference and Workshop Papers", "access": "closed", "key": "conf/pkdd/DevosMD19", "doi": "10.1007/978-3-030-46150-8_35", "ee": "https://doi.org/10.1007/978-3-030-46150-8_35", "url": "https://dblp.org/rec/conf/pkdd/DevosMD19"}, "url": "URL#994645"}, {"@score": "1", "@id": "994649", "info": {"authors": {"author": [{"@pid": "264/0182", "text": "Guillaume Doquet"}, {"@pid": "s/MicheleSebag", "text": "Mich\u00e8le Sebag"}]}, "title": "Agnostic Feature Selection.", "venue": "ECML/PKDD", "pages": "343-358", "year": "2019", "type": "Conference and Workshop Papers", "access": "closed", "key": "conf/pkdd/DoquetS19", "doi": "10.1007/978-3-030-46150-8_21", "ee": "https://doi.org/10.1007/978-3-030-46150-8_21", "url": "https://dblp.org/rec/conf/pkdd/DoquetS19"}, "url": "URL#994649"}, {"@score": "1", "@id": "994657", "info": {"authors": {"author": [{"@pid": "126/2373", "text": "Wenjie Feng"}, {"@pid": "32/2527", "text": "Shenghua Liu"}, {"@pid": "44/912", "text": "Xueqi Cheng"}]}, "title": "CatchCore - Catching Hierarchical Dense Subtensor.", "venue": "ECML/PKDD", "pages": "156-172", "year": "2019", "type": "Conference and Workshop Papers", "access": "closed", "key": "conf/pkdd/FengLC19", "doi": "10.1007/978-3-030-46150-8_10", "ee": "https://doi.org/10.1007/978-3-030-46150-8_10", "url": "https://dblp.org/rec/conf/pkdd/FengLC19"}, "url": "URL#994657"}, {"@score": "1", "@id": "994658", "info": {"authors": {"author": [{"@pid": "185/1315", "text": "Len Feremans"}, {"@pid": "206/3254", "text": "Vincent Vercruyssen"}, {"@pid": "61/7047", "text": "Boris Cule"}, {"@pid": "82/334", "text": "Wannes Meert"}, {"@pid": "g/BartGoethals", "text": "Bart Goethals"}]}, "title": "Pattern-Based Anomaly Detection in Mixed-Type Time Series.", "venue": "ECML/PKDD", "pages": "240-256", "year": "2019", "type": "Conference and Workshop Papers", "access": "closed", "key": "conf/pkdd/FeremansVCMG19", "doi": "10.1007/978-3-030-46150-8_15", "ee": "https://doi.org/10.1007/978-3-030-46150-8_15", "url": "https://dblp.org/rec/conf/pkdd/FeremansVCMG19"}, "url": "URL#994658"}, {"@score": "1", "@id": "994662", "info": {"authors": {"author": [{"@pid": "68/10701", "text": "Jonas Fischer"}, {"@pid": "94/6462", "text": "Jilles Vreeken"}]}, "title": "Sets of Robust Rules, and How to Find Them.", "venue": "ECML/PKDD", "pages": "38-54", "year": "2019", "type": "Conference and Workshop Papers", "access": "closed", "key": "conf/pkdd/FischerV19", "doi": "10.1007/978-3-030-46150-8_3", "ee": "https://doi.org/10.1007/978-3-030-46150-8_3", "url": "https://dblp.org/rec/conf/pkdd/FischerV19"}, "url": "URL#994662"}, {"@score": "1", "@id": "994664", "info": {"authors": {"author": [{"@pid": "188/6806", "text": "Satoshi Furutani"}, {"@pid": "168/9586", "text": "Toshiki Shibahara"}, {"@pid": "26/3158", "text": "Mitsuaki Akiyama"}, {"@pid": "129/1031", "text": "Kunio Hato"}, {"@pid": "67/15", "text": "Masaki Aida"}]}, "title": "Graph Signal Processing for Directed Graphs Based on the Hermitian Laplacian.", "venue": "ECML/PKDD", "pages": "447-463", "year": "2019", "type": "Conference and Workshop Papers", "access": "closed", "key": "conf/pkdd/FurutaniSAHA19", "doi": "10.1007/978-3-030-46150-8_27", "ee": "https://doi.org/10.1007/978-3-030-46150-8_27", "url": "https://dblp.org/rec/conf/pkdd/FurutaniSAHA19"}, "url": "URL#994664"}, {"@score": "1", "@id": "994666", "info": {"authors": {"author": [{"@pid": "178/4440", "text": "Zahra Ghafoori"}, {"@pid": "07/1057", "text": "James C. Bezdek"}, {"@pid": "73/1139", "text": "Christopher Leckie"}, {"@pid": "47/5584", "text": "Shanika Karunasekera"}]}, "title": "Unsupervised and Active Learning Using Maximin-Based Anomaly Detection.", "venue": "ECML/PKDD", "pages": "90-106", "year": "2019", "type": "Conference and Workshop Papers", "access": "closed", "key": "conf/pkdd/GhafooriBLK19", "doi": "10.1007/978-3-030-46150-8_6", "ee": "https://doi.org/10.1007/978-3-030-46150-8_6", "url": "https://dblp.org/rec/conf/pkdd/GhafooriBLK19"}, "url": "URL#994666"}, {"@score": "1", "@id": "994671", "info": {"authors": {"author": [{"@pid": "264/0274", "text": "Luce le Gorrec"}, {"@pid": "34/2688", "text": "Sandrine Mouysset"}, {"@pid": "75/821", "text": "Iain S. Duff"}, {"@pid": "85/5012", "text": "Philip A. Knight"}, {"@pid": "88/5512-2", "text": "Daniel Ruiz 0002"}]}, "title": "Uncovering Hidden Block Structure for Clustering.", "venue": "ECML/PKDD", "pages": "140-155", "year": "2019", "type": "Conference and Workshop Papers", "access": "closed", "key": "conf/pkdd/GorrecMDK019", "doi": "10.1007/978-3-030-46150-8_9", "ee": "https://doi.org/10.1007/978-3-030-46150-8_9", "url": "https://dblp.org/rec/conf/pkdd/GorrecMDK019"}, "url": "URL#994671"}, {"@score": "1", "@id": "994674", "info": {"authors": {"author": [{"@pid": "157/9871", "text": "Riccardo Guidotti"}, {"@pid": "40/1533", "text": "Anna Monreale"}, {"@pid": "m/StanMatwin", "text": "Stan Matwin"}, {"@pid": "p/DPedreschi", "text": "Dino Pedreschi"}]}, "title": "Black Box Explanation by Learning Image Exemplars in the Latent Feature Space.", "venue": "ECML/PKDD", "pages": "189-205", "year": "2019", "type": "Conference and Workshop Papers", "access": "closed", "key": "conf/pkdd/GuidottiMMP19", "doi": "10.1007/978-3-030-46150-8_12", "ee": "https://doi.org/10.1007/978-3-030-46150-8_12", "url": "https://dblp.org/rec/conf/pkdd/GuidottiMMP19"}, "url": "URL#994674"}, {"@score": "1", "@id": "994680", "info": {"authors": {"author": [{"@pid": "151/2087", "text": "Sibylle Hess"}, {"@pid": "23/1341", "text": "Wouter Duivesteijn"}]}, "title": "k Is the Magic Number - Inferring the Number of Clusters Through Nonparametric Concentration Inequalities.", "venue": "ECML/PKDD", "pages": "257-273", "year": "2019", "type": "Conference and Workshop Papers", "access": "closed", "key": "conf/pkdd/HessD19", "doi": "10.1007/978-3-030-46150-8_16", "ee": "https://doi.org/10.1007/978-3-030-46150-8_16", "url": "https://dblp.org/rec/conf/pkdd/HessD19"}, "url": "URL#994680"}, {"@score": "1", "@id": "994682", "info": {"authors": {"author": [{"@pid": "h/FrankHoppner", "text": "Frank H\u00f6ppner"}, {"@pid": "263/3657", "text": "Maximilian Jahnke"}]}, "title": "Holistic Assessment of Structure Discovery Capabilities of Clustering Algorithms.", "venue": "ECML/PKDD", "pages": "223-239", "year": "2019", "type": "Conference and Workshop Papers", "access": "closed", "key": "conf/pkdd/HoppnerJ19", "doi": "10.1007/978-3-030-46150-8_14", "ee": "https://doi.org/10.1007/978-3-030-46150-8_14", "url": "https://dblp.org/rec/conf/pkdd/HoppnerJ19"}, "url": "URL#994682"}, {"@score": "1", "@id": "994686", "info": {"authors": {"author": [{"@pid": "172/7746", "text": "Babak Hosseini"}, {"@pid": "h/BarbaraHammer", "text": "Barbara Hammer"}]}, "title": "Interpretable Discriminative Dimensionality Reduction and Feature Selection on the Manifold.", "venue": "ECML/PKDD", "pages": "310-326", "year": "2019", "type": "Conference and Workshop Papers", "access": "closed", "key": "conf/pkdd/HosseiniH19", "doi": "10.1007/978-3-030-46150-8_19", "ee": "https://doi.org/10.1007/978-3-030-46150-8_19", "url": "https://dblp.org/rec/conf/pkdd/HosseiniH19"}, "url": "URL#994686"}, {"@score": "1", "@id": "994690", "info": {"authors": {"author": [{"@pid": "18/7116", "text": "Sungjin Im"}, {"@pid": "260/0357", "text": "Mahshid Montazer Qaem"}]}, "title": "Fast and Parallelizable Ranking with Outliers from Pairwise Comparisons.", "venue": "ECML/PKDD", "pages": "173-188", "year": "2019", "type": "Conference and Workshop Papers", "access": "closed", "key": "conf/pkdd/ImQ19", "doi": "10.1007/978-3-030-46150-8_11", "ee": "https://doi.org/10.1007/978-3-030-46150-8_11", "url": "https://dblp.org/rec/conf/pkdd/ImQ19"}, "url": "URL#994690"}, {"@score": "1", "@id": "994691", "info": {"authors": {"author": [{"@pid": "234/1560", "text": "S. Indrapriyadarsini"}, {"@pid": "234/1309", "text": "Shahrzad Mahboubi"}, {"@pid": "56/5588", "text": "Hiroshi Ninomiya"}, {"@pid": "37/3926", "text": "Hideki Asai"}]}, "title": "A Stochastic Quasi-Newton Method with Nesterov&apos;s Accelerated Gradient.", "venue": "ECML/PKDD", "pages": "743-760", "year": "2019", "type": "Conference and Workshop Papers", "access": "closed", "key": "conf/pkdd/Indrapriyadarsini19", "doi": "10.1007/978-3-030-46150-8_43", "ee": "https://doi.org/10.1007/978-3-030-46150-8_43", "url": "https://dblp.org/rec/conf/pkdd/Indrapriyadarsini19"}, "url": "URL#994691"}, {"@score": "1", "@id": "994699", "info": {"authors": {"author": [{"@pid": "67/1861", "text": "Di Jin"}, {"@pid": "215/4357", "text": "Mark Heimann"}, {"@pid": "17/5085", "text": "Ryan A. Rossi"}, {"@pid": "91/9987", "text": "Danai Koutra"}]}, "title": "node2bits - Compact Time- and Attribute-Aware Node Representations for User Stitching.", "venue": "ECML/PKDD", "pages": "483-506", "year": "2019", "type": "Conference and Workshop Papers", "access": "closed", "key": "conf/pkdd/JinHRK19", "doi": "10.1007/978-3-030-46150-8_29", "ee": "https://doi.org/10.1007/978-3-030-46150-8_29", "url": "https://dblp.org/rec/conf/pkdd/JinHRK19"}, "url": "URL#994699"}, {"@score": "1", "@id": "994710", "info": {"authors": {"author": [{"@pid": "71/9649", "text": "Megha Khosla"}, {"@pid": "218/0241", "text": "Jurek Leonhardt"}, {"@pid": "n/WolfgangNejdl", "text": "Wolfgang Nejdl"}, {"@pid": "02/7062", "text": "Avishek Anand"}]}, "title": "Node Representation Learning for Directed Graphs.", "venue": "ECML/PKDD", "pages": "395-411", "year": "2019", "type": "Conference and Workshop Papers", "access": "closed", "key": "conf/pkdd/KhoslaLNA19", "doi": "10.1007/978-3-030-46150-8_24", "ee": "https://doi.org/10.1007/978-3-030-46150-8_24", "url": "https://dblp.org/rec/conf/pkdd/KhoslaLNA19"}, "url": "URL#994710"}, {"@score": "1", "@id": "994714", "info": {"authors": {"author": [{"@pid": "236/5191", "text": "Dmitry Kobak"}, {"@pid": "81/9445", "text": "George C. Linderman"}, {"@pid": "08/8050", "text": "Stefan Steinerberger"}, {"@pid": "79/5739", "text": "Yuval Kluger"}, {"@pid": "78/3560", "text": "Philipp Berens"}]}, "title": "Heavy-Tailed Kernels Reveal a Finer Cluster Structure in t-SNE Visualisations.", "venue": "ECML/PKDD", "pages": "124-139", "year": "2019", "type": "Conference and Workshop Papers", "access": "open", "key": "conf/pkdd/KobakLSKB19", "doi": "10.1007/978-3-030-46150-8_8", "ee": "https://doi.org/10.1007/978-3-030-46150-8_8", "url": "https://dblp.org/rec/conf/pkdd/KobakLSKB19"}, "url": "URL#994714"}, {"@score": "1", "@id": "994723", "info": {"authors": {"author": [{"@pid": "177/7195", "text": "Nishma Laitonjam"}, {"@pid": "205/1911", "text": "Weip\u00e9ng Hu\u00e1ng"}, {"@pid": "86/2778", "text": "Neil J. Hurley"}]}, "title": "A Soft Affiliation Graph Model for Scalable Overlapping Community Detection.", "venue": "ECML/PKDD", "pages": "507-523", "year": "2019", "type": "Conference and Workshop Papers", "access": "closed", "key": "conf/pkdd/LaitonjamHH19", "doi": "10.1007/978-3-030-46150-8_30", "ee": "https://doi.org/10.1007/978-3-030-46150-8_30", "url": "https://dblp.org/rec/conf/pkdd/LaitonjamHH19"}, "url": "URL#994723"}, {"@score": "1", "@id": "994726", "info": {"authors": {"author": [{"@pid": "46/6611", "text": "Silvio Lattanzi"}, {"@pid": "257/4172", "text": "Thomas Lavastida"}, {"@pid": "147/3348", "text": "Kefu Lu"}, {"@pid": "28/5638", "text": "Benjamin Moseley"}]}, "title": "A Framework for Parallelizing Hierarchical Clustering Methods.", "venue": "ECML/PKDD", "pages": "73-89", "year": "2019", "type": "Conference and Workshop Papers", "access": "closed", "key": "conf/pkdd/LattanziLLM19", "doi": "10.1007/978-3-030-46150-8_5", "ee": "https://doi.org/10.1007/978-3-030-46150-8_5", "url": "https://dblp.org/rec/conf/pkdd/LattanziLLM19"}, "url": "URL#994726"}, {"@score": "1", "@id": "994743", "info": {"authors": {"author": [{"@pid": "245/2906", "text": "Vijaikumar M"}, {"@pid": "66/6214", "text": "Shirish K. Shevade"}, {"@pid": "m/MNarasimhaMurty", "text": "M. Narasimha Murty"}]}, "title": "SoRecGAT - Leveraging Graph Attention Mechanism for Top-N Social Recommendation.", "venue": "ECML/PKDD", "pages": "430-446", "year": "2019", "type": "Conference and Workshop Papers", "access": "closed", "key": "conf/pkdd/MSM19", "doi": "10.1007/978-3-030-46150-8_26", "ee": "https://doi.org/10.1007/978-3-030-46150-8_26", "url": "https://dblp.org/rec/conf/pkdd/MSM19"}, "url": "URL#994743"}, {"@score": "1", "@id": "994766", "info": {"authors": {"author": [{"@pid": "64/6487", "text": "Atsuyoshi Nakamura"}, {"@pid": "261/5998", "text": "Kento Sakurada"}]}, "title": "An Algorithm for Reducing the Number of Distinct Branching Conditions in a Decision Forest.", "venue": "ECML/PKDD", "pages": "578-589", "year": "2019", "type": "Conference and Workshop Papers", "access": "closed", "key": "conf/pkdd/NakamuraS19", "doi": "10.1007/978-3-030-46150-8_34", "ee": "https://doi.org/10.1007/978-3-030-46150-8_34", "url": "https://dblp.org/rec/conf/pkdd/NakamuraS19"}, "url": "URL#994766"}, {"@score": "1", "@id": "994802", "info": {"authors": {"author": [{"@pid": "140/2833", "text": "Anant Raj"}, {"@pid": "200/9045", "text": "Ho Chung Leon Law"}, {"@pid": "31/1783", "text": "Dino Sejdinovic"}, {"@pid": "20/10800", "text": "Mijung Park"}]}, "title": "A Differentially Private Kernel Two-Sample Test.", "venue": "ECML/PKDD", "pages": "697-724", "year": "2019", "type": "Conference and Workshop Papers", "access": "closed", "key": "conf/pkdd/RajLSP19", "doi": "10.1007/978-3-030-46150-8_41", "ee": "https://doi.org/10.1007/978-3-030-46150-8_41", "url": "https://dblp.org/rec/conf/pkdd/RajLSP19"}, "url": "URL#994802"}, {"@score": "1", "@id": "994810", "info": {"authors": {"author": [{"@pid": "225/0932", "text": "Krzysztof Rudas"}, {"@pid": "41/5897", "text": "Szymon Jaroszewicz"}]}, "title": "Shrinkage Estimators for Uplift Regression.", "venue": "ECML/PKDD", "pages": "607-623", "year": "2019", "type": "Conference and Workshop Papers", "access": "closed", "key": "conf/pkdd/RudasJ19", "doi": "10.1007/978-3-030-46150-8_36", "ee": "https://doi.org/10.1007/978-3-030-46150-8_36", "url": "https://dblp.org/rec/conf/pkdd/RudasJ19"}, "url": "URL#994810"}, {"@score": "1", "@id": "994811", "info": {"authors": {"author": [{"@pid": "242/4220", "text": "Amal Saadallah"}, {"@pid": "264/0353", "text": "Florian Priebe"}, {"@pid": "m/KatharinaMorik", "text": "Katharina Morik"}]}, "title": "A Drift-Based Dynamic Ensemble Members Selection Using Clustering for Time Series Forecasting.", "venue": "ECML/PKDD", "pages": "678-694", "year": "2019", "type": "Conference and Workshop Papers", "access": "closed", "key": "conf/pkdd/SaadallahPM19", "doi": "10.1007/978-3-030-46150-8_40", "ee": "https://doi.org/10.1007/978-3-030-46150-8_40", "url": "https://dblp.org/rec/conf/pkdd/SaadallahPM19"}, "url": "URL#994811"}, {"@score": "1", "@id": "994812", "info": {"authors": {"author": [{"@pid": "244/1991", "text": "Mojdeh Saadati"}, {"@pid": "04/4658-1", "text": "Jin Tian 0001"}]}, "title": "Adjustment Criteria for Recovering Causal Effects from Missing Data.", "venue": "ECML/PKDD", "pages": "561-577", "year": "2019", "type": "Conference and Workshop Papers", "access": "closed", "key": "conf/pkdd/SaadatiT19", "doi": "10.1007/978-3-030-46150-8_33", "ee": "https://doi.org/10.1007/978-3-030-46150-8_33", "url": "https://dblp.org/rec/conf/pkdd/SaadatiT19"}, "url": "URL#994812"}, {"@score": "1", "@id": "994824", "info": {"authors": {"author": [{"@pid": "97/9987", "text": "Konstantinos Sechidis"}, {"@pid": "227/3880", "text": "Konstantinos Papangelou"}, {"@pid": "163/2961", "text": "Sarah Nogueira"}, {"@pid": "133/7401", "text": "James Weatherall"}, {"@pid": "93/2057-1", "text": "Gavin Brown 0001"}]}, "title": "On the Stability of Feature Selection in the Presence of Feature Correlations.", "venue": "ECML/PKDD", "pages": "327-342", "year": "2019", "type": "Conference and Workshop Papers", "access": "closed", "key": "conf/pkdd/SechidisPNW019", "doi": "10.1007/978-3-030-46150-8_20", "ee": "https://doi.org/10.1007/978-3-030-46150-8_20", "url": "https://dblp.org/rec/conf/pkdd/SechidisPNW019"}, "url": "URL#994824"}, {"@score": "1", "@id": "994825", "info": {"authors": {"author": [{"@pid": "256/5399", "text": "Florian Seiffarth"}, {"@pid": "55/6464-1", "text": "Tam\u00e1s Horv\u00e1th 0001"}, {"@pid": "w/StefanWrobel", "text": "Stefan Wrobel"}]}, "title": "Maximal Closed Set and Half-Space Separations in Finite Closure Systems.", "venue": "ECML/PKDD", "pages": "21-37", "year": "2019", "type": "Conference and Workshop Papers", "access": "closed", "key": "conf/pkdd/Seiffarth0W19", "doi": "10.1007/978-3-030-46150-8_2", "ee": "https://doi.org/10.1007/978-3-030-46150-8_2", "url": "https://dblp.org/rec/conf/pkdd/Seiffarth0W19"}, "url": "URL#994825"}, {"@score": "1", "@id": "994829", "info": {"authors": {"author": [{"@pid": "55/4736", "text": "Yu Shi"}, {"@pid": "217/2180", "text": "Xinwei He"}, {"@pid": "139/1435", "text": "Naijing Zhang"}, {"@pid": "162/0187", "text": "Carl Yang"}, {"@pid": "h/JiaweiHan", "text": "Jiawei Han 0001"}]}, "title": "User-Guided Clustering in Heterogeneous Information Networks via Motif-Based Comprehensive Transcription.", "venue": "ECML/PKDD", "pages": "361-377", "year": "2019", "type": "Conference and Workshop Papers", "access": "closed", "key": "conf/pkdd/ShiHZY019", "doi": "10.1007/978-3-030-46150-8_22", "ee": "https://doi.org/10.1007/978-3-030-46150-8_22", "url": "https://dblp.org/rec/conf/pkdd/ShiHZY019"}, "url": "URL#994829"}, {"@score": "1", "@id": "994830", "info": {"authors": {"author": [{"@pid": "264/0336", "text": "Hadar Sivan"}, {"@pid": "117/8009", "text": "Moshe Gabel"}, {"@pid": "s/AssafSchuster", "text": "Assaf Schuster"}]}, "title": "Online Linear Models for Edge Computing.", "venue": "ECML/PKDD", "pages": "645-661", "year": "2019", "type": "Conference and Workshop Papers", "access": "closed", "key": "conf/pkdd/SivanGS19", "doi": "10.1007/978-3-030-46150-8_38", "ee": "https://doi.org/10.1007/978-3-030-46150-8_38", "url": "https://dblp.org/rec/conf/pkdd/SivanGS19"}, "url": "URL#994830"}, {"@score": "1", "@id": "994836", "info": {"authors": {"author": {"@pid": "28/488", "text": "Nikolaj Tatti"}}, "title": "Fast Likelihood-Based Change Point Detection.", "venue": "ECML/PKDD", "pages": "662-677", "year": "2019", "type": "Conference and Workshop Papers", "access": "closed", "key": "conf/pkdd/Tatti19", "doi": "10.1007/978-3-030-46150-8_39", "ee": "https://doi.org/10.1007/978-3-030-46150-8_39", "url": "https://dblp.org/rec/conf/pkdd/Tatti19"}, "url": "URL#994836"}, {"@score": "1", "@id": "994843", "info": {"authors": {"author": [{"@pid": "29/5273", "text": "Charalampos E. Tsourakakis"}, {"@pid": "93/4437", "text": "Tianyi Chen"}, {"@pid": "45/4449", "text": "Naonori Kakimura"}, {"@pid": "140/7314", "text": "Jakub Pachocki"}]}, "title": "Novel Dense Subgraph Discovery Primitives - Risk Aversion and Exclusion Queries.", "venue": "ECML/PKDD", "pages": "378-394", "year": "2019", "type": "Conference and Workshop Papers", "access": "closed", "key": "conf/pkdd/TsourakakisCKP19", "doi": "10.1007/978-3-030-46150-8_23", "ee": "https://doi.org/10.1007/978-3-030-46150-8_23", "url": "https://dblp.org/rec/conf/pkdd/TsourakakisCKP19"}, "url": "URL#994843"}, {"@score": "1", "@id": "994867", "info": {"authors": {"author": [{"@pid": "54/7712", "text": "Hongjing Zhang"}, {"@pid": "76/5024", "text": "Sugato Basu"}, {"@pid": "81/2360", "text": "Ian Davidson"}]}, "title": "A Framework for Deep Constrained Clustering - Algorithms and Advances.", "venue": "ECML/PKDD", "pages": "57-72", "year": "2019", "type": "Conference and Workshop Papers", "access": "closed", "key": "conf/pkdd/ZhangBD19", "doi": "10.1007/978-3-030-46150-8_4", "ee": "https://doi.org/10.1007/978-3-030-46150-8_4", "url": "https://dblp.org/rec/conf/pkdd/ZhangBD19"}, "url": "URL#994867"}, {"@score": "1", "@id": "994868", "info": {"authors": {"author": [{"@pid": "97/8704-116", "text": "Lei Zhang 0116"}, {"@pid": "97/3618", "text": "Shupeng Wang"}, {"@pid": "68/3340", "text": "Xin Jin"}, {"@pid": "185/5714", "text": "Siyu Jia"}]}, "title": "Joint Multi-source Reduction.", "venue": "ECML/PKDD", "pages": "293-309", "year": "2019", "type": "Conference and Workshop Papers", "access": "closed", "key": "conf/pkdd/ZhangWJJ19", "doi": "10.1007/978-3-030-46150-8_18", "ee": "https://doi.org/10.1007/978-3-030-46150-8_18", "url": "https://dblp.org/rec/conf/pkdd/ZhangWJJ19"}, "url": "URL#994868"}]}}}